bobolink/__init__.py
bobolink/api.py
bobolink/main.py
bobolink-0.2.0.dist-info/entry_points.txt
bobolink-0.2.0.dist-info/WHEEL
bobolink-0.2.0.dist-info/METADATA
bobolink-0.2.0.dist-info/RECORD
