Metadata-Version: 2.1
Name: bobolink
Version: 0.2.0
Summary: bobolink stores bookmarks and helps you search for them later
Home-page: https://github.com/jtanza/bobolink-cli
License: MIT
Author: jtanza
Author-email: tanzajohn@gmail.com
Requires-Python: >=3.8,<4.0
Classifier: License :: OSI Approved :: MIT License
Classifier: Programming Language :: Python :: 3
Classifier: Programming Language :: Python :: 3.8
Classifier: Programming Language :: Python :: 3.9
Requires-Dist: click (>=7.1.2,<8.0.0)
Requires-Dist: requests (>=2.25.1,<3.0.0)
Requires-Dist: termcolor (>=1.1.0,<2.0.0)
Project-URL: Repository, https://github.com/jtanza/bobolink-cli
